tifex_py/__init__.py
tifex_py/feature_extraction/__init__.py
tifex_py/feature_extraction/data.py
tifex_py/feature_extraction/extraction.py
tifex_py/feature_extraction/settings.py
tifex_py/feature_extraction/spectral_feature_calculators.py
tifex_py/feature_extraction/statistical_feature_calculators.py
tifex_py/feature_extraction/time_frequency_feature_calculators.py
tifex_py/utils/__init__.py
tifex_py/utils/decorators.py
tifex_py/utils/extraction_utils.py
tifex_py-0.1.1.dist-info/LICENSE.txt
tifex_py-0.1.1.dist-info/METADATA
tifex_py-0.1.1.dist-info/WHEEL
tifex_py-0.1.1.dist-info/top_level.txt
tifex_py-0.1.1.dist-info/RECORD
