Metadata-Version: 2.1
Name: tifex-py
Version: 0.1.1
Summary: TODO
Author-email: Mehdi Ejtehadi <TODO@gmail.com>, Gloria Edumaba Graham <edumabagrahamp@gmail.com>, Cailin Ringstrom <cringstrom@ethz.ch>
Maintainer-email: TODO <TODO@gmail.com>
License: MIT LICENCE
Project-URL: Repository, https://github.com/SCAI-Lab/proj-adl-classification/tree/main
Keywords: feature,extraction
Classifier: License :: OSI Approved :: MIT License
Classifier: Programming Language :: Python
Classifier: Programming Language :: Python :: 3
License-File: LICENSE.txt
Requires-Dist: scipy
Requires-Dist: statsmodels
Requires-Dist: numpy
Requires-Dist: librosa
Requires-Dist: PyWavelets
Requires-Dist: PyYAML
